wink_sdk_affiliate/__init__.py
wink_sdk_affiliate/api_client.py
wink_sdk_affiliate/api_response.py
wink_sdk_affiliate/configuration.py
wink_sdk_affiliate/exceptions.py
wink_sdk_affiliate/py.typed
wink_sdk_affiliate/rest.py
wink_sdk_affiliate/api/__init__.py
wink_sdk_affiliate/api/account_manager_api.py
wink_sdk_affiliate/api/affiliate_api.py
wink_sdk_affiliate/api/leads_api.py
wink_sdk_affiliate/api/notification_api.py
wink_sdk_affiliate/api/travel_agent_api.py
wink_sdk_affiliate/models/__init__.py
wink_sdk_affiliate/models/address_affiliate.py
wink_sdk_affiliate/models/address_agent.py
wink_sdk_affiliate/models/address_supplier.py
wink_sdk_affiliate/models/affiliate_account_affiliate.py
wink_sdk_affiliate/models/affiliate_account_agent.py
wink_sdk_affiliate/models/affiliate_account_supplier.py
wink_sdk_affiliate/models/affiliate_account_user_affiliate.py
wink_sdk_affiliate/models/affiliate_account_user_agent.py
wink_sdk_affiliate/models/affiliate_account_user_supplier.py
wink_sdk_affiliate/models/aggregate_descriptor_supplier.py
wink_sdk_affiliate/models/auto_base_unit_steps_supplier.py
wink_sdk_affiliate/models/axis_line_supplier.py
wink_sdk_affiliate/models/axis_ticks_supplier.py
wink_sdk_affiliate/models/booking_analytics_supplier.py
wink_sdk_affiliate/models/booking_overview_request_supplier.py
wink_sdk_affiliate/models/border_supplier.py
wink_sdk_affiliate/models/category_axis_crosshair_supplier.py
wink_sdk_affiliate/models/category_axis_crosshair_tooltip_supplier.py
wink_sdk_affiliate/models/category_axis_notes_icon_supplier.py
wink_sdk_affiliate/models/category_axis_notes_label_supplier.py
wink_sdk_affiliate/models/category_axis_notes_supplier.py
wink_sdk_affiliate/models/category_axis_select_supplier.py
wink_sdk_affiliate/models/category_axis_title_supplier.py
wink_sdk_affiliate/models/chart_category_axis_labels_supplier.py
wink_sdk_affiliate/models/chart_category_axis_major_grid_lines_supplier.py
wink_sdk_affiliate/models/chart_category_axis_supplier.py
wink_sdk_affiliate-0.0.57.dist-info/licenses/LICENSE
wink_sdk_affiliate-0.0.57.dist-info/METADATA
wink_sdk_affiliate-0.0.57.dist-info/WHEEL
wink_sdk_affiliate-0.0.57.dist-info/top_level.txt
wink_sdk_affiliate-0.0.57.dist-info/RECORD
